engame/__main__.py
engame/pairs.py
engame/yq.py
engame-0.1.0.dist-info/METADATA
engame-0.1.0.dist-info/WHEEL
engame-0.1.0.dist-info/entry_points.txt
engame-0.1.0.dist-info/RECORD
