Metadata-Version: 2.1
Name: eNGame
Version: 0.1.0
Summary: 
License: GPLv3 or later
Author: Daniel Lenski
Author-email: dlenski@gmail.com
Requires-Python: >=3.9,<4.0
Classifier: License :: Other/Proprietary License
Classifier: Programming Language :: Python :: 3
Classifier: Programming Language :: Python :: 3.9
Classifier: Programming Language :: Python :: 3.10
Classifier: Programming Language :: Python :: 3.11
Classifier: Programming Language :: Python :: 3.12
Requires-Dist: colored (>=2.0,<3.0)
Requires-Dist: requests
